paypal/__init__.py
paypal/compat.py
paypal/countries.py
paypal/exceptions.py
paypal/interface.py
paypal/response.py
paypal/response_list.py
paypal/settings.py
paypal-1.2.5.dist-info/DESCRIPTION.rst
paypal-1.2.5.dist-info/METADATA
paypal-1.2.5.dist-info/RECORD
paypal-1.2.5.dist-info/WHEEL
paypal-1.2.5.dist-info/metadata.json
paypal-1.2.5.dist-info/top_level.txt
